pass_pad
