Metadata-Version: 1.0
Name: pass-pad
Version: 0.0.2.4
Summary: 密码本
Home-page: https://blog.csdn.net/hfcaoguilin
Author: prgrmz07
Author-email: prgrmz07@163.com
License: UNKNOWN
Platform: UNKNOWN
